README.md
setup.cfg
setup.py
themis_ml/__init__.py
themis_ml/checks.py
themis_ml/meta_estimators.py
themis_ml/metrics.py
themis_ml/stats_utils.py
themis_ml.egg-info/PKG-INFO
themis_ml.egg-info/SOURCES.txt
themis_ml.egg-info/dependency_links.txt
themis_ml.egg-info/requires.txt
themis_ml.egg-info/top_level.txt
themis_ml/datasets/__init__.py
themis_ml/datasets/census_income_data_map.py
themis_ml/datasets/data_types.py
themis_ml/datasets/datasets.py
themis_ml/datasets/german_credit_data_map.py
themis_ml/datasets/data/census_income_1994_1995_test.csv
themis_ml/datasets/data/census_income_1994_1995_train.csv
themis_ml/datasets/data/german_credit.csv
themis_ml/linear_model/__init__.py
themis_ml/linear_model/counterfactually_fair_models.py
themis_ml/postprocessing/__init__.py
themis_ml/postprocessing/reject_option_classification.py
themis_ml/preprocessing/__init__.py
themis_ml/preprocessing/relabelling.py