Metadata-Version: 1.1
Name: themis-ml
Version: 0.0.4
Summary: Fairness-aware Machine Learning
Home-page: https://github.com/cosmicBboy/themis-ml
Author: Niels Bantilan
Author-email: niels.bantilan@gmail.com
License: MIT
Download-URL: https://github.com/cosmicBboy/themis-ml/archive/0.0.2.tar.gz
Keywords: machine-learning,fairness-aware,social-bias
Platform: UNKNOWN
